owid/catalog/__init__.py
owid/catalog/catalogs.py
owid/catalog/charts.py
owid/catalog/datasets.py
owid/catalog/internal.py
owid/catalog/jinja.py
owid/catalog/meta.py
owid/catalog/processing.py
owid/catalog/processing_log.py
owid/catalog/properties.py
owid/catalog/s3_utils.py
owid/catalog/tables.py
owid/catalog/utils.py
owid/catalog/variables.py
owid/catalog/warnings.py
owid/catalog/yaml_metadata.py
owid/catalog/schemas/table.json
owid/catalog/schemas/variable.json
owid_catalog-0.4.5.dist-info/METADATA
owid_catalog-0.4.5.dist-info/WHEEL
owid_catalog-0.4.5.dist-info/licenses/LICENSE
owid_catalog-0.4.5.dist-info/RECORD
