Metadata-Version: 2.4
Name: owid-catalog
Version: 0.4.5
Summary: Core data types used by OWID for managing data.
Project-URL: Homepage, https://github.com/owid/etl/tree/master/lib/catalog
Project-URL: Repository, https://github.com/etl/etl.git
Author-email: Our World in Data <tech@ourworldindata.org>
License-Expression: MIT
License-File: LICENSE
Requires-Python: <4.0,>=3.10
Requires-Dist: dataclasses-json>=0.6.7
Requires-Dist: dynamic-yaml>=1.3.5
Requires-Dist: ipdb>=0.13.9
Requires-Dist: jinja2>=3.1.6
Requires-Dist: jsonschema>=3.2.0
Requires-Dist: mistune>=3.0.1
Requires-Dist: owid-datautils
Requires-Dist: owid-repack
Requires-Dist: pandas>=2.2.3
Requires-Dist: pyarrow>=10.0.1
Requires-Dist: pyreadr>=0.5.0
Requires-Dist: pyyaml>=6.0.1
Requires-Dist: rapidfuzz>=3.14.3
Requires-Dist: rdata>=0.11.2
Requires-Dist: requests>=2.26.0
Requires-Dist: structlog>=21.5.0
Requires-Dist: typing-extensions>=4.7.1
Requires-Dist: unidecode>=1.3.4
